[
{"i":2300,"domain":"education","summary":"World Bank HOI for reading proficiency level 3 in private schools."},
{"i":2301,"domain":"education","summary":"World Bank HOI for reading proficiency level 3 in public schools."},
{"i":2302,"domain":"natural_resources","summary":"World Bank Human Opportunities Index for sanitation access capturing inequality across groups."},
{"i":2303,"domain":"education","summary":"World Bank Human Opportunities Index for school enrollment capturing inequality across groups."},
{"i":2304,"domain":"education","summary":"World Bank HOI for science proficiency level 2 capturing inequality across groups."},
{"i":2305,"domain":"education","summary":"World Bank HOI for science proficiency level 2 in private schools."},
{"i":2306,"domain":"education","summary":"World Bank HOI for science proficiency level 2 in public schools."},
{"i":2307,"domain":"education","summary":"World Bank HOI for science proficiency level 3 capturing inequality across groups."},
{"i":2308,"domain":"education","summary":"World Bank HOI for science proficiency level 3 in private schools."},
{"i":2309,"domain":"education","summary":"World Bank HOI for science proficiency level 3 in public schools."},
{"i":2310,"domain":"natural_resources","summary":"World Bank Human Opportunities Index for water access capturing inequality across groups."},
{"i":2311,"domain":"education","summary":"World Bank pre-primary gross enrollment rate from national sources as percentage."},
{"i":2312,"domain":"energy","summary":"World Bank share of renewable energy in total final energy consumption."},
{"i":2313,"domain":"education","summary":"World Bank gross intake ratio into grade 1 of primary education from national sources."},
{"i":2314,"domain":"education","summary":"World Bank gender parity index for gross intake ratio in primary grade 1."},
{"i":2315,"domain":"education","summary":"World Bank rate of children of primary age not enrolled in primary or secondary school."},
{"i":2316,"domain":"education","summary":"World Bank primary completion rate as percentage of relevant age group from national sources."},
{"i":2317,"domain":"education","summary":"World Bank gender parity index for primary completion rate."},
{"i":2318,"domain":"education","summary":"World Bank progression rate to secondary school from national sources."},
{"i":2319,"domain":"education","summary":"World Bank lower secondary completion rate as percentage of relevant age group."},
{"i":2320,"domain":"demographics","summary":"World Bank Atkinson inequality index with aversion parameter epsilon=0.5."},
{"i":2321,"domain":"demographics","summary":"World Bank Atkinson inequality index with aversion parameter epsilon=1."},
{"i":2322,"domain":"demographics","summary":"World Bank Atkinson inequality index with aversion parameter epsilon=2."},
{"i":2323,"domain":"demographics","summary":"World Bank Generalized Entropy inequality index GE(-1)."},
{"i":2324,"domain":"demographics","summary":"World Bank Generalized Entropy inequality index GE(2)."},
{"i":2325,"domain":"demographics","summary":"World Bank Gini coefficient of income inequality based on Lorenz curve."},
{"i":2326,"domain":"demographics","summary":"World Bank Gini coefficient excluding zero-income observations."},
{"i":2327,"domain":"demographics","summary":"World Bank share of household income held by the bottom 20 percent quintile."},
{"i":2328,"domain":"demographics","summary":"World Bank share of household income held by the second income quintile (20-40%)."},
{"i":2329,"domain":"demographics","summary":"World Bank share of household income held by the third income quintile (40-60%)."},
{"i":2330,"domain":"demographics","summary":"World Bank share of household income held by the fourth income quintile (60-80%)."},
{"i":2331,"domain":"demographics","summary":"World Bank share of household income held by the top quintile (80-100%)."},
{"i":2332,"domain":"demographics","summary":"World Bank Mean Log Deviation inequality measure GE(0)."},
{"i":2333,"domain":"demographics","summary":"World Bank decile dispersion ratio of average income of richest 25% to poorest 25%."},
{"i":2334,"domain":"demographics","summary":"World Bank decile dispersion ratio of average income of richest 10% to poorest 10%."},
{"i":2335,"domain":"demographics","summary":"World Bank Theil inequality index GE(1), additive across subgroups."},
{"i":2336,"domain":"demographics","summary":"World Bank rural Gini coefficient of income inequality."},
{"i":2337,"domain":"demographics","summary":"World Bank rural Mean Log Deviation inequality measure GE(0)."},
{"i":2338,"domain":"demographics","summary":"World Bank rural Theil inequality index GE(1)."},
{"i":2339,"domain":"education","summary":"World Bank count of new first-time lower secondary teachers from national sources."},
{"i":2340,"domain":"education","summary":"World Bank count of first-time primary school entrants excluding repeaters."},
{"i":2341,"domain":"energy","summary":"World Bank renewable energy consumption in terajoules across all renewable technologies."},
{"i":2342,"domain":"education","summary":"World Bank count of lower secondary classrooms from national sources."},
{"i":2343,"domain":"education","summary":"World Bank count of newly built lower secondary classrooms from national sources."},
{"i":2344,"domain":"education","summary":"World Bank ratio of mathematics textbooks per pupil in primary education."},
{"i":2345,"domain":"education","summary":"World Bank ratio of language textbooks per pupil in primary education."},
{"i":2346,"domain":"education","summary":"World Bank year of last study on effective learning time and teacher attendance."},
{"i":2347,"domain":"demographics","summary":"World Bank urban Gini coefficient of income inequality."},
{"i":2348,"domain":"demographics","summary":"World Bank urban Mean Log Deviation inequality measure GE(0)."},
{"i":2349,"domain":"demographics","summary":"World Bank urban Theil inequality index GE(1)."},
{"i":2350,"domain":"education","summary":"World Bank total count of pupils in primary school from national sources."},
{"i":2351,"domain":"education","summary":"World Bank count of primary school teachers from national sources."},
{"i":2352,"domain":"education","summary":"World Bank count of new first-time primary school teachers from national sources."},
{"i":2353,"domain":"education","summary":"World Bank count of primary school classrooms from national sources."},
{"i":2354,"domain":"education","summary":"World Bank count of newly built primary school classrooms from national sources."},
{"i":2355,"domain":"education","summary":"World Bank count of first-time lower secondary school entrants excluding repeaters."},
{"i":2356,"domain":"education","summary":"World Bank total count of pupils in lower secondary school from national sources."},
{"i":2357,"domain":"education","summary":"World Bank count of lower secondary school teachers from national sources."},
{"i":2358,"domain":"labor","summary":"World Bank share of population aged 15-18 neither employed nor in school."},
{"i":2359,"domain":"labor","summary":"World Bank share of population aged 15-24 neither employed nor in school."},
{"i":2360,"domain":"labor","summary":"World Bank share of population aged 19-24 neither employed nor in school."},
{"i":2361,"domain":"labor","summary":"World Bank share of population aged 15-18 in school and not employed."},
{"i":2362,"domain":"labor","summary":"World Bank share of population aged 15-24 in school and not employed."},
{"i":2363,"domain":"labor","summary":"World Bank share of population aged 19-24 in school and not employed."},
{"i":2364,"domain":"labor","summary":"World Bank share of population aged 15-18 who are both in school and employed."},
{"i":2365,"domain":"labor","summary":"World Bank share of population aged 15-24 who are both in school and employed."},
{"i":2366,"domain":"labor","summary":"World Bank share of population aged 19-24 who are both in school and employed."},
{"i":2367,"domain":"labor","summary":"World Bank share of population aged 15-18 employed and not in school."},
{"i":2368,"domain":"labor","summary":"World Bank share of population aged 15-24 employed and not in school."},
{"i":2369,"domain":"labor","summary":"World Bank share of population aged 19-24 employed and not in school."},
{"i":2370,"domain":"energy","summary":"World Bank total electricity output in gigawatt-hours generated by all power plants."},
{"i":2371,"domain":"energy","summary":"World Bank electricity output in GWh from renewable power plants."},
{"i":2372,"domain":"labor","summary":"World Bank share of male population aged 15-18 neither employed nor in school."},
{"i":2373,"domain":"labor","summary":"World Bank share of male population aged 15-24 neither employed nor in school."},
{"i":2374,"domain":"labor","summary":"World Bank share of male population aged 19-24 neither employed nor in school."},
{"i":2375,"domain":"labor","summary":"World Bank share of male population aged 15-18 in school and not employed."},
{"i":2376,"domain":"labor","summary":"World Bank share of male population aged 15-24 in school and not employed."},
{"i":2377,"domain":"labor","summary":"World Bank share of male population aged 19-24 in school and not employed."},
{"i":2378,"domain":"labor","summary":"World Bank share of male population aged 15-18 both in school and employed."},
{"i":2379,"domain":"labor","summary":"World Bank share of male population aged 15-24 both in school and employed."},
{"i":2380,"domain":"labor","summary":"World Bank share of male population aged 19-24 both in school and employed."},
{"i":2381,"domain":"labor","summary":"World Bank share of male population aged 15-18 employed and not in school."},
{"i":2382,"domain":"labor","summary":"World Bank share of male population aged 15-24 employed and not in school."},
{"i":2383,"domain":"labor","summary":"World Bank share of male population aged 19-24 employed and not in school."},
{"i":2384,"domain":"energy","summary":"World Bank share of renewable electricity generation in total electricity output."},
{"i":2385,"domain":"education","summary":"World Bank public education spending as percentage of total public spending."},
{"i":2386,"domain":"labor","summary":"World Bank share of female population aged 15-18 neither employed nor in school."},
{"i":2387,"domain":"labor","summary":"World Bank share of female population aged 15-24 neither employed nor in school."},
{"i":2388,"domain":"labor","summary":"World Bank share of female population aged 19-24 neither employed nor in school."},
{"i":2389,"domain":"labor","summary":"World Bank share of female population aged 15-18 in school and not employed."},
{"i":2390,"domain":"labor","summary":"World Bank share of female population aged 15-24 in school and not employed."},
{"i":2391,"domain":"labor","summary":"World Bank share of female population aged 19-24 in school and not employed."},
{"i":2392,"domain":"labor","summary":"World Bank share of female population aged 15-18 both in school and employed."},
{"i":2393,"domain":"labor","summary":"World Bank share of female population aged 15-24 both in school and employed."},
{"i":2394,"domain":"labor","summary":"World Bank share of female population aged 19-24 both in school and employed."},
{"i":2395,"domain":"labor","summary":"World Bank share of female population aged 15-18 employed and not in school."},
{"i":2396,"domain":"labor","summary":"World Bank share of female population aged 15-24 employed and not in school."},
{"i":2397,"domain":"labor","summary":"World Bank share of female population aged 19-24 employed and not in school."},
{"i":2398,"domain":"education","summary":"World Bank public basic education spending as percentage of total education spending."},
{"i":2399,"domain":"education","summary":"World Bank public recurrent education spending as percentage of total public recurrent spending."}
]
