[
{"i": 3844, "domain": "housing", "summary": "Utah building footprints with height floors and notes."},
{"i": 3846, "domain": "transportation", "summary": "Utah local unpaved roads with maintenance, county, and federal route info."},
{"i": 3847, "domain": "environment", "summary": "Utah washout feature inventory with construction status."},
{"i": 3848, "domain": "housing", "summary": "Utah plat hook points at 1:125 scale."},
{"i": 3850, "domain": "housing", "summary": "Utah May tax parcel snapshots with subdivision and sale year."},
{"i": 3851, "domain": "public_safety", "summary": "Utah mosquito light trap species counts with duplicate species fields."},
{"i": 3852, "domain": "natural_resources", "summary": "Utah open space with amenities (tennis, pickleball, bocci, daycare)."},
{"i": 3853, "domain": "natural_resources", "summary": "Utah irrigation swing joint inventory with company and size."},
{"i": 3855, "domain": "legal", "summary": "Utah PLSS section polygons with town, range, and area."},
{"i": 3856, "domain": "environment", "summary": "Utah Underground Injection Control well inventory by parcel and property class."},
{"i": 3857, "domain": "technology", "summary": "Utah white background map feature at 1:288K scale."},
{"i": 3858, "domain": "housing", "summary": "Utah live parcel line features with COGO radius and side."},
{"i": 3859, "domain": "housing", "summary": "Utah live parcel line features with COGO distance, tangent, and direction."},
{"i": 3860, "domain": "education", "summary": "Utah daycare and preschool directory with address and phone."},
{"i": 3861, "domain": "natural_resources", "summary": "Utah clayey soil polygons with composition and scoring."},
{"i": 3862, "domain": "demographics", "summary": "Utah city limits at large scale with name."},
{"i": 3864, "domain": "elections", "summary": "Utah Vista ballot precinct area version 2 boundaries."},
{"i": 3866, "domain": "transportation", "summary": "Utah county road pavement condition (RRAMS) at 1:9K with horizontal alignment."},
{"i": 3868, "domain": "housing", "summary": "Utah plat hook points at 1:250 scale."},
{"i": 3869, "domain": "housing", "summary": "South Jordan City, Utah owned parcels with market and taxable value (2017)."},
{"i": 3870, "domain": "demographics", "summary": "Utah city limits at large scale with name."},
{"i": 3871, "domain": "natural_resources", "summary": "Utah watershed basin boundary polygons."},
{"i": 3872, "domain": "housing", "summary": "Utah building footprints with height floors, within municipality, and usage type."},
{"i": 3874, "domain": "housing", "summary": "Utah parcels with market value change, agricultural land value, and year built."},
{"i": 3876, "domain": "housing", "summary": "Utah parcel boundaries at 1:9K scale with source and book/page."},
{"i": 3877, "domain": "natural_resources", "summary": "Utah SITLA suggested camping area locations in La Sal Mountains."},
{"i": 3878, "domain": "transportation", "summary": "Sandy, Utah roads not plowed by city."},
{"i": 3880, "domain": "legal", "summary": "Utah cemeteries with acres, burial counts, and owner contacts."},
{"i": 3881, "domain": "education", "summary": "Utah middle school attendance boundaries."},
{"i": 3882, "domain": "transportation", "summary": "Utah county road pavement condition (RRAMS) at 1:2K with bus route and bike lane."},
{"i": 3883, "domain": "education", "summary": "Utah health and medical admin services graduate salaries by university."},
{"i": 3885, "domain": "environment", "summary": "Utah storm SCADA asset inventory with stem condition and inspection date."},
{"i": 3886, "domain": "finance", "summary": "Utah monthly LLC registration counts processed by Commerce Department."},
{"i": 3887, "domain": "housing", "summary": "Utah master address points with apartment, year built, and municipality code."},
{"i": 3888, "domain": "energy", "summary": "Utah pipeline inventory with operator ID and subsystem name."},
{"i": 3889, "domain": "natural_resources", "summary": "Utah landslide scarp features with map scale and publication date."},
{"i": 3890, "domain": "environment", "summary": "Utah storm drain structures with grate size, shape, and manhole type."},
{"i": 3891, "domain": "environment", "summary": "Utah storm drain pipe inventory with CUES score and pipe size."},
{"i": 3892, "domain": "housing", "summary": "Utah live parcel line features with COGO radius and side."},
{"i": 3893, "domain": "environment", "summary": "Utah approximate 100-year flood (1% annual chance) polygons with flood depth and velocity."},
{"i": 3897, "domain": "transportation", "summary": "Utah county road pavement condition (RRAMS) at 1:1K with lane widths."},
{"i": 3899, "domain": "energy", "summary": "Utah electrical junction box asset inventory with ownership and GPS date."},
{"i": 3900, "domain": "natural_resources", "summary": "Utah park facility sites at 1:1K scale with trail map and owner type."},
{"i": 3901, "domain": "legal", "summary": "Utah deed recording points at 1:1K scale."},
{"i": 3902, "domain": "demographics", "summary": "Utah city border polygons with label and square miles."},
{"i": 3903, "domain": "education", "summary": "Utah Local Education Agency (LEA) modeling neighborhood polygons."},
{"i": 3905, "domain": "public_safety", "summary": "Utah fire hydrant inventory with residual pressure and 20/30 PSI flow."},
{"i": 3906, "domain": "housing", "summary": "Utah parcels with property class, market value, structure condition, and taxes."},
{"i": 3907, "domain": "housing", "summary": "Utah site plan review records with address, status, and approval date."},
{"i": 3910, "domain": "legal", "summary": "Utah cemeteries with acres, hectares, first burial, and contacts."},
{"i": 3911, "domain": "housing", "summary": "Utah priority area zoning polygons with zone code and acreage."},
{"i": 3912, "domain": "transportation", "summary": "Utah secondary road network."},
{"i": 3913, "domain": "environment", "summary": "Utah flood control access project inventory with project name and year."},
{"i": 3914, "domain": "health", "summary": "Utah low-income health clinic directory with address and phone."},
{"i": 3915, "domain": "natural_resources", "summary": "Utah golf course rough area asset inventory."},
{"i": 3916, "domain": "environment", "summary": "Utah storm drain pipe inventory with pipe condition and criticality score."},
{"i": 3917, "domain": "environment", "summary": "Utah storm drain detention basin as-built with use, capacity, and date."},
{"i": 3918, "domain": "natural_resources", "summary": "Utah groundwater secondary recharge zone boundaries."},
{"i": 3919, "domain": "transportation", "summary": "Utah paved county road network with full road name and municipality."},
{"i": 3920, "domain": "transportation", "summary": "Utah signs flagged for inspection with speed limit and MUTCD description."},
{"i": 3921, "domain": "natural_resources", "summary": "Sandy, Utah city-managed parks with amenities and lighting details."},
{"i": 3924, "domain": "public_safety", "summary": "Utah mosquito light traps by trap number and location."},
{"i": 3925, "domain": "demographics", "summary": "Utah city border polygons with square miles."},
{"i": 3926, "domain": "demographics", "summary": "Utah median income from 2010 Census by tract."},
{"i": 3927, "domain": "public_safety", "summary": "Utah Corrections jail bed performance measures on requests and supervision."},
{"i": 3928, "domain": "education", "summary": "Utah LPN and nursing assistants one-year tech college graduate salaries."},
{"i": 3930, "domain": "transportation", "summary": "Utah short-list street hazard remediation locations with phone and inspection info."},
{"i": 3931, "domain": "transportation", "summary": "Utah street centerline features with maintenance and zip."},
{"i": 3932, "domain": "education", "summary": "Utah healthcare associate degree graduate salaries by school."},
{"i": 3933, "domain": "natural_resources", "summary": "Utah West Desert Columbia Basin 1989 land use shapefile (DWR)."},
{"i": 3935, "domain": "housing", "summary": "Utah parcels with greenbelt qualified, taxes owed, and vesting document."},
{"i": 3936, "domain": "environment", "summary": "Utah retrofitted water quality infrastructure project inventory."},
{"i": 3937, "domain": "legal", "summary": "Utah deed recording points with book/page and parcel ID."},
{"i": 3938, "domain": "transportation", "summary": "Utah snow removal area assignments with road miles and rotation."},
{"i": 3939, "domain": "transportation", "summary": "Sandy, Utah roads not plowed (duplicate layer)."},
{"i": 3940, "domain": "housing", "summary": "Utah Department of Workforce Services construction and housing performance measures."},
{"i": 3941, "domain": "transportation", "summary": "Utah county road pavement condition (RRAMS) at 1:500 scale."},
{"i": 3943, "domain": "environment", "summary": "Utah stormwater outfall inventory with receiving waters and structural condition."},
{"i": 3946, "domain": "public_safety", "summary": "Utah fire hydrant inventory with provider, static pressure, and size."},
{"i": 3948, "domain": "natural_resources", "summary": "Utah 250-foot topographic contour lines with elevation."},
{"i": 3949, "domain": "finance", "summary": "Utah State Auditor's Office performance management outcome measures."},
{"i": 3950, "domain": "transportation", "summary": "Utah street centerline features with zip, surface, and editor."},
{"i": 3952, "domain": "legal", "summary": "Utah PLSS section polygons with township, range, and quarter section labels."},
{"i": 3954, "domain": "housing", "summary": "Utah building inventory with ownership, address, and type."},
{"i": 3955, "domain": "transportation", "summary": "Utah concrete sidewalk locations with short-list waterway and root cuts."},
{"i": 3957, "domain": "public_safety", "summary": "Utah mosquito service customer contacts with email and street."},
{"i": 3959, "domain": "legal", "summary": "Utah code inspection district boundaries with officer and business counts."},
{"i": 3960, "domain": "natural_resources", "summary": "Utah water pump station inventory with flow (GPM) and zones."},
{"i": 3961, "domain": "public_safety", "summary": "Utah fire hydrant inventory with depth, pressure, and inspection date."},
{"i": 3962, "domain": "housing", "summary": "Utah subdivision records with lots, acres, and final approval."},
{"i": 3964, "domain": "natural_resources", "summary": "Utah trailhead locations with trail name."},
{"i": 3965, "domain": "demographics", "summary": "Sandy, Utah solid border polygon."},
{"i": 3966, "domain": "environment", "summary": "Utah stormwater outfall inventory with pipe material and elevation."},
{"i": 3967, "domain": "natural_resources", "summary": "Utah North Dry Creek pressurized irrigation line inventory."},
{"i": 3969, "domain": "transportation", "summary": "Utah street centerline features with speed limit and source."},
{"i": 3970, "domain": "transportation", "summary": "Utah county road pavement condition (RRAMS) at 1:500 scale with inspection comments."},
{"i": 3973, "domain": "transportation", "summary": "Utah cul-de-sac point features."},
{"i": 3974, "domain": "environment", "summary": "Utah stormwater separator inventory with invert, type, and ownership."},
{"i": 3975, "domain": "legal", "summary": "Utah mapper areas by township, range, section, and book."},
{"i": 3976, "domain": "demographics", "summary": "Utah county boundary labels at 1:9K scale with railroad name and FIPS."}
]
