[
{"i": 527, "domain": "health", "summary": "WHO global indicator for compliance of ban on advertising at point of sale by country and year."},
{"i": 529, "domain": "health", "summary": "WHO global indicator for ban on tobacco advertising on internet by country and year."},
{"i": 533, "domain": "health", "summary": "WHO global indicator for compliance with bans on direct advertising by country and year."},
{"i": 534, "domain": "health", "summary": "WHO global indicator for electric field (kV/m) by country and year."},
{"i": 535, "domain": "health", "summary": "WHO global indicator for electric field limit at 1800 MHz (V/m) by country and year."},
{"i": 541, "domain": "health", "summary": "WHO global indicator for number of new G2D leprosy cases by country and year."},
{"i": 543, "domain": "health", "summary": "WHO global indicator for status of endemicity of Taenia solium by country and year."},
{"i": 546, "domain": "health", "summary": "WHO global indicator for children under 5 stunted by country and year."},
{"i": 549, "domain": "health", "summary": "WHO global indicator for educational attainment in prevention by country and year."},
{"i": 551, "domain": "health", "summary": "WHO global indicator for continuing professional development in prevention by country and year."},
{"i": 552, "domain": "health", "summary": "WHO global indicator for educational attainment in treatment by country and year."},
{"i": 558, "domain": "health", "summary": "WHO global indicator for status of endemicity of onchocerciasis by country and year."},
{"i": 560, "domain": "health", "summary": "WHO global indicator for status of pinta endemicity by country and year."},
{"i": 561, "domain": "health", "summary": "WHO global indicator for reported number of human rabies deaths by country and year."},
{"i": 562, "domain": "agriculture", "summary": "WHO global indicator for presence of porcine cysticercosis by country and year."},
{"i": 570, "domain": "health", "summary": "WHO global indicator for open access interventions for drugs by country and year."},
{"i": 572, "domain": "health", "summary": "WHO global indicator for postgraduate training programme in treatment by country and year."},
{"i": 573, "domain": "health", "summary": "WHO global indicator for exclusive breastfeeding under 6 months by country and year."},
{"i": 578, "domain": "health", "summary": "WHO global indicator for NGOs for alcohol use disorders by country and year."},
{"i": 580, "domain": "health", "summary": "WHO global indicator for self-help groups for substance use disorders by country and year."},
{"i": 597, "domain": "health", "summary": "WHO global indicator for employment services for drug use disorders by country and year."},
{"i": 598, "domain": "health", "summary": "WHO global indicator for open access interventions for alcohol by country and year."},
{"i": 601, "domain": "health", "summary": "WHO global indicator for harm reduction programmes for IDUs by country and year."},
{"i": 603, "domain": "health", "summary": "WHO global indicator for standards of care for health professionals by country and year."},
{"i": 604, "domain": "health", "summary": "WHO global indicator for service delivery data collection for substance use by country and year."},
{"i": 610, "domain": "health", "summary": "WHO global indicator for bupropion place available by country and year."},
{"i": 614, "domain": "health", "summary": "WHO global indicator for estimate of daily tobacco use prevalence by country and year."},
{"i": 615, "domain": "health", "summary": "WHO global indicator for daily tobacco smoking crude adjusted by country and year."},
{"i": 616, "domain": "health", "summary": "WHO global indicator for monitoring tobacco use and prevention policies by country and year."},
{"i": 617, "domain": "health", "summary": "WHO global indicator for adult survey age range smokeless by country and year."},
{"i": 618, "domain": "health", "summary": "WHO global indicator for adult smokeless tobacco use definition by country and year."},
{"i": 619, "domain": "health", "summary": "WHO global indicator for youth smokeless tobacco use definition by country and year."},
{"i": 620, "domain": "health", "summary": "WHO global indicator for name of survey of youth smokeless by country and year."},
{"i": 621, "domain": "health", "summary": "WHO global indicator for year of survey of adults smokeless by country and year."},
{"i": 622, "domain": "health", "summary": "WHO global indicator for name of survey of youth by country and year."},
{"i": 623, "domain": "health", "summary": "WHO global indicator for representativeness of survey of adults by country and year."},
{"i": 624, "domain": "health", "summary": "WHO global indicator for estimated number of malaria cases by country and year."},
{"i": 628, "domain": "health", "summary": "WHO global indicator for malaria incidence per 100,000 by country and year."},
{"i": 629, "domain": "health", "summary": "WHO global indicator for adolescent birth rate per 1000 women by country and year."},
{"i": 633, "domain": "health", "summary": "WHO global indicator for tuberculosis treatment success under DOTS by country and year."},
{"i": 634, "domain": "health", "summary": "WHO global indicator for maternal mortality ratio per 100,000 live births by country and year."},
{"i": 636, "domain": "health", "summary": "WHO global indicator for total published dementia research output by country and year."},
{"i": 641, "domain": "health", "summary": "WHO global indicator for existence of dementia sub-national plans by country and year."},
{"i": 646, "domain": "health", "summary": "WHO global indicator for offering help to quit tobacco use by country and year."},
{"i": 653, "domain": "health", "summary": "WHO global indicator for nicotine replacement therapy legally sold by country and year."},
{"i": 654, "domain": "health", "summary": "WHO global indicator for access to a toll-free quit line by country and year."},
{"i": 655, "domain": "health", "summary": "WHO global indicator for varenicline cost covered by country and year."},
{"i": 656, "domain": "health", "summary": "WHO global indicator for varenicline legally sold by country and year."},
{"i": 657, "domain": "health", "summary": "WHO global indicator for bupropion legally sold by country and year."},
{"i": 659, "domain": "health", "summary": "WHO global indicator for nicotine replacement therapy place available by country and year."},
{"i": 662, "domain": "health", "summary": "WHO global indicator for alcohol lifetime abstainers by country and year."},
{"i": 663, "domain": "health", "summary": "WHO global indicator for alcohol abstainers past 12 months by country and year."},
{"i": 665, "domain": "health", "summary": "WHO global indicator for alcohol former drinkers by country and year."},
{"i": 666, "domain": "health", "summary": "WHO global indicator for alcohol patterns of drinking score by country and year."},
{"i": 667, "domain": "health", "summary": "WHO global indicator for alcohol patterns of drinking score by country and year."},
{"i": 670, "domain": "health", "summary": "WHO global indicator for nicotine replacement therapy cost covered by country and year."},
{"i": 671, "domain": "health", "summary": "WHO global indicator for varenicline place available by country and year."},
{"i": 685, "domain": "health", "summary": "WHO global indicator for alcohol consumers past 12 months by country and year."},
{"i": 686, "domain": "health", "summary": "WHO global indicator for number of neurologists per 100,000 by country and year."},
{"i": 691, "domain": "health", "summary": "WHO global indicator for age-standardized DALYs falls per 100,000 by country and year."},
{"i": 694, "domain": "health", "summary": "WHO global indicator for alcohol abstainers lifetime age-standardized by country and year."},
{"i": 695, "domain": "health", "summary": "WHO global indicator for abstainers 15-19 lifetime by country and year."},
{"i": 700, "domain": "health", "summary": "WHO global indicator for abstainers 15-19 past 12 months by country and year."},
{"i": 705, "domain": "health", "summary": "WHO global indicator for leprosy number of cases registered for treatment by country and year."},
{"i": 709, "domain": "agriculture", "summary": "WHO global indicator for practice of backyard pig production by country and year."},
{"i": 710, "domain": "health", "summary": "WHO global indicator for number of cases of yaws reported by country and year."},
{"i": 712, "domain": "health", "summary": "WHO global indicator for children under 5 wasted for age by country and year."},
{"i": 713, "domain": "health", "summary": "WHO global indicator for essential list of medicines by country and year."},
{"i": 715, "domain": "health", "summary": "WHO global indicator for budget line for substance use disorder prevention by country and year."},
{"i": 719, "domain": "health", "summary": "WHO global indicator for postgraduate training programme in prevention by country and year."},
{"i": 722, "domain": "health", "summary": "WHO global indicator for clinical supervision of health care staff by country and year."},
{"i": 723, "domain": "health", "summary": "WHO global indicator for continuing professional development in treatment by country and year."},
{"i": 724, "domain": "health", "summary": "WHO global indicator for epidemiological data collection for substance use by country and year."},
{"i": 728, "domain": "finance", "summary": "WHO global indicator for donor commitments in millions of 2009 USD by country and year."},
{"i": 731, "domain": "labor", "summary": "WHO global indicator for occupational risk factors attributable deaths by country and year."},
{"i": 732, "domain": "labor", "summary": "WHO global indicator for occupational carcinogens attributable DALYs by country and year."},
{"i": 734, "domain": "labor", "summary": "WHO global indicator for occupational noise attributable DALYs by country and year."},
{"i": 737, "domain": "labor", "summary": "WHO global indicator for occupational injuries attributable deaths by country and year."},
{"i": 742, "domain": "health", "summary": "WHO global indicator for kidney transplants per million by country and year."},
{"i": 743, "domain": "health", "summary": "WHO global indicator for liver transplants per million by country and year."},
{"i": 744, "domain": "demographics", "summary": "WHO global indicator for population in millions by country and year."},
{"i": 745, "domain": "health", "summary": "WHO global indicator for total actual deceased donors by country and year."},
{"i": 748, "domain": "finance", "summary": "WHO global indicator for donor disbursements in millions of 2009 USD by country and year."},
{"i": 750, "domain": "health", "summary": "WHO global indicator for liver transplants absolute number by country and year."},
{"i": 751, "domain": "health", "summary": "WHO global indicator for total organs transplanted per million by country and year."},
{"i": 753, "domain": "health", "summary": "WHO global indicator for kidney transplants absolute number by country and year."},
{"i": 754, "domain": "health", "summary": "WHO global indicator for total organs transplanted absolute number by country and year."},
{"i": 756, "domain": "health", "summary": "WHO global indicator for national smoking ban number of smoke-free places by country and year."},
{"i": 757, "domain": "health", "summary": "WHO global indicator for national smoking ban in indoor offices by country and year."},
{"i": 761, "domain": "health", "summary": "WHO global indicator for dementia care facilities hospitals by country and year."},
{"i": 762, "domain": "health", "summary": "WHO global indicator for care facilities hospice centres by country and year."},
{"i": 763, "domain": "health", "summary": "WHO global indicator for outpatient health centres by country and year."},
{"i": 765, "domain": "health", "summary": "WHO global indicator for total dementia hospital admissions per 100,000 by country and year."},
{"i": 768, "domain": "public_safety", "summary": "WHO global indicator for age-standardized DALYs fires per 100,000 by country and year."},
{"i": 775, "domain": "health", "summary": "WHO global indicator for protecting people from tobacco smoke by country and year."},
{"i": 777, "domain": "health", "summary": "WHO global indicator for national smoking ban fines on establishment by country and year."},
{"i": 779, "domain": "health", "summary": "WHO global indicator for outpatient social centres by country and year."},
{"i": 782, "domain": "health", "summary": "WHO global indicator for age-standardized DALYs poisoning per 100,000 by country and year."},
{"i": 788, "domain": "public_safety", "summary": "WHO global indicator for age-standardized DALYs violence per 100,000 by country and year."},
{"i": 791, "domain": "public_safety", "summary": "WHO global indicator for age-standardized death rates fires per 100,000 by country and year."}
]
