[
{"i": 1557, "domain": "finance", "summary": "World Bank coverage of social protection and labor programs as percent of population by country."},
{"i": 1558, "domain": "finance", "summary": "World Bank generosity of social protection and labor programs by country."},
{"i": 1559, "domain": "health", "summary": "World Bank prevalence of persons aged 15-29 with functional difficulties by country."},
{"i": 1560, "domain": "health", "summary": "World Bank prevalence of persons aged 30-44 with functional difficulties by country."},
{"i": 1561, "domain": "health", "summary": "World Bank prevalence of persons aged 45-64 with functional difficulties by country."},
{"i": 1562, "domain": "health", "summary": "World Bank prevalence of persons aged 65+ with functional difficulties by country."},
{"i": 1563, "domain": "health", "summary": "World Bank prevalence of persons with any functional difficulties by country."},
{"i": 1564, "domain": "health", "summary": "World Bank prevalence of persons aged 15-29 with cognitive difficulty by country."},
{"i": 1565, "domain": "health", "summary": "World Bank prevalence of persons aged 30-44 with cognitive difficulty by country."},
{"i": 1566, "domain": "health", "summary": "World Bank prevalence of persons aged 45-64 with cognitive difficulty by country."},
{"i": 1567, "domain": "health", "summary": "World Bank prevalence of persons aged 65+ with cognitive difficulty by country."},
{"i": 1568, "domain": "health", "summary": "World Bank prevalence of persons with any cognitive difficulty by country."},
{"i": 1569, "domain": "health", "summary": "World Bank prevalence of female persons with cognitive difficulty by country."},
{"i": 1570, "domain": "health", "summary": "World Bank prevalence of male persons with cognitive difficulty by country."},
{"i": 1571, "domain": "health", "summary": "World Bank prevalence of rural persons with cognitive difficulty by country."},
{"i": 1572, "domain": "health", "summary": "World Bank prevalence of urban persons with cognitive difficulty by country."},
{"i": 1573, "domain": "health", "summary": "World Bank prevalence of persons aged 15-29 with communication difficulty by country."},
{"i": 1574, "domain": "health", "summary": "World Bank prevalence of persons aged 30-44 with communication difficulty by country."},
{"i": 1575, "domain": "health", "summary": "World Bank prevalence of persons aged 45-64 with communication difficulty by country."},
{"i": 1576, "domain": "health", "summary": "World Bank prevalence of persons aged 65+ with communication difficulty by country."},
{"i": 1577, "domain": "health", "summary": "World Bank prevalence of persons with any communication difficulty by country."},
{"i": 1578, "domain": "health", "summary": "World Bank prevalence of female persons with communication difficulty by country."},
{"i": 1579, "domain": "health", "summary": "World Bank prevalence of male persons with communication difficulty by country."},
{"i": 1580, "domain": "health", "summary": "World Bank prevalence of rural persons with communication difficulty by country."},
{"i": 1581, "domain": "health", "summary": "World Bank prevalence of urban persons with communication difficulty by country."},
{"i": 1582, "domain": "health", "summary": "World Bank prevalence of female persons with functional difficulty by country."},
{"i": 1583, "domain": "health", "summary": "World Bank prevalence of persons aged 15-29 with hearing difficulty by country."},
{"i": 1584, "domain": "health", "summary": "World Bank prevalence of persons aged 30-44 with hearing difficulty by country."},
{"i": 1585, "domain": "health", "summary": "World Bank prevalence of persons aged 45-64 with hearing difficulty by country."},
{"i": 1586, "domain": "health", "summary": "World Bank prevalence of persons aged 65+ with hearing difficulty by country."},
{"i": 1587, "domain": "health", "summary": "World Bank prevalence of persons with any hearing difficulty by country."},
{"i": 1588, "domain": "health", "summary": "World Bank prevalence of female persons with hearing difficulty by country."},
{"i": 1589, "domain": "health", "summary": "World Bank prevalence of male persons with hearing difficulty by country."},
{"i": 1590, "domain": "health", "summary": "World Bank prevalence of rural persons with hearing difficulty by country."},
{"i": 1591, "domain": "health", "summary": "World Bank prevalence of urban persons with hearing difficulty by country."},
{"i": 1592, "domain": "health", "summary": "World Bank prevalence of male persons with functional difficulty by country."},
{"i": 1593, "domain": "health", "summary": "World Bank prevalence of persons aged 15-29 with mobility difficulty by country."},
{"i": 1594, "domain": "health", "summary": "World Bank prevalence of persons aged 30-44 with mobility difficulty by country."},
{"i": 1595, "domain": "health", "summary": "World Bank prevalence of persons aged 45-64 with mobility difficulty by country."},
{"i": 1596, "domain": "health", "summary": "World Bank prevalence of persons aged 65+ with mobility difficulty by country."},
{"i": 1597, "domain": "health", "summary": "World Bank prevalence of persons with any mobility difficulty by country."},
{"i": 1598, "domain": "health", "summary": "World Bank prevalence of female persons with mobility difficulty by country."},
{"i": 1599, "domain": "health", "summary": "World Bank prevalence of male persons with mobility difficulty by country."},
{"i": 1600, "domain": "health", "summary": "World Bank prevalence of rural persons with mobility difficulty by country."},
{"i": 1601, "domain": "health", "summary": "World Bank prevalence of urban persons with mobility difficulty by country."},
{"i": 1602, "domain": "health", "summary": "World Bank prevalence of rural persons with functional difficulty by country."},
{"i": 1603, "domain": "health", "summary": "World Bank prevalence of persons aged 15-29 with seeing difficulty by country."},
{"i": 1604, "domain": "health", "summary": "World Bank prevalence of persons aged 30-44 with seeing difficulty by country."},
{"i": 1605, "domain": "health", "summary": "World Bank prevalence of persons aged 45-64 with seeing difficulty by country."},
{"i": 1606, "domain": "health", "summary": "World Bank prevalence of persons aged 65+ with seeing difficulty by country."},
{"i": 1607, "domain": "health", "summary": "World Bank prevalence of persons with any seeing difficulty by country."},
{"i": 1608, "domain": "health", "summary": "World Bank prevalence of female persons with seeing difficulty by country."},
{"i": 1609, "domain": "health", "summary": "World Bank prevalence of male persons with seeing difficulty by country."},
{"i": 1610, "domain": "health", "summary": "World Bank prevalence of rural persons with seeing difficulty by country."},
{"i": 1611, "domain": "health", "summary": "World Bank prevalence of urban persons with seeing difficulty by country."},
{"i": 1612, "domain": "health", "summary": "World Bank prevalence of persons aged 15-29 with selfcare difficulty by country."},
{"i": 1613, "domain": "health", "summary": "World Bank prevalence of persons aged 30-44 with selfcare difficulty by country."},
{"i": 1614, "domain": "health", "summary": "World Bank prevalence of persons aged 45-64 with selfcare difficulty by country."},
{"i": 1615, "domain": "health", "summary": "World Bank prevalence of persons aged 65+ with selfcare difficulty by country."},
{"i": 1616, "domain": "health", "summary": "World Bank prevalence of persons with any selfcare difficulty by country."},
{"i": 1617, "domain": "health", "summary": "World Bank prevalence of female persons with selfcare difficulty by country."},
{"i": 1618, "domain": "health", "summary": "World Bank prevalence of male persons with selfcare difficulty by country."},
{"i": 1619, "domain": "health", "summary": "World Bank prevalence of rural persons with selfcare difficulty by country."},
{"i": 1620, "domain": "health", "summary": "World Bank prevalence of urban persons with selfcare difficulty by country."},
{"i": 1621, "domain": "health", "summary": "World Bank prevalence of urban persons with functional difficulty by country."},
{"i": 1622, "domain": "public_safety", "summary": "World Bank women aged 15-29 with disabilities subjected to violence in last 12 months by country."},
{"i": 1623, "domain": "public_safety", "summary": "World Bank women aged 30-44 with disabilities subjected to violence in last 12 months by country."},
{"i": 1624, "domain": "public_safety", "summary": "World Bank women with disabilities subjected to violence in last 12 months by country."},
{"i": 1625, "domain": "public_safety", "summary": "World Bank rural women with disabilities subjected to violence in last 12 months by country."},
{"i": 1626, "domain": "public_safety", "summary": "World Bank urban women with disabilities subjected to violence in last 12 months by country."},
{"i": 1627, "domain": "public_safety", "summary": "World Bank women aged 15-29 with functional difficulty subjected to violence in last 12 months by country."},
{"i": 1628, "domain": "public_safety", "summary": "World Bank women aged 30-44 with functional difficulty subjected to violence in last 12 months by country."},
{"i": 1629, "domain": "public_safety", "summary": "World Bank women with functional difficulty subjected to violence in last 12 months by country."},
{"i": 1630, "domain": "public_safety", "summary": "World Bank women with cognitive difficulty subjected to violence in last 12 months by country."},
{"i": 1631, "domain": "public_safety", "summary": "World Bank women with communication difficulty subjected to violence in last 12 months by country."},
{"i": 1632, "domain": "public_safety", "summary": "World Bank women with hearing difficulty subjected to violence in last 12 months by country."},
{"i": 1633, "domain": "public_safety", "summary": "World Bank women with mobility difficulty subjected to violence in last 12 months by country."},
{"i": 1634, "domain": "public_safety", "summary": "World Bank rural women with functional difficulty subjected to violence in last 12 months by country."},
{"i": 1635, "domain": "public_safety", "summary": "World Bank women with seeing difficulty subjected to violence in last 12 months by country."},
{"i": 1636, "domain": "public_safety", "summary": "World Bank women with selfcare difficulty subjected to violence in last 12 months by country."},
{"i": 1637, "domain": "public_safety", "summary": "World Bank urban women with functional difficulty subjected to violence in last 12 months by country."},
{"i": 1638, "domain": "public_safety", "summary": "World Bank women aged 15-29 with no functional difficulty subjected to violence in last 12 months by country."},
{"i": 1639, "domain": "public_safety", "summary": "World Bank women aged 30-44 with no functional difficulty subjected to violence in last 12 months by country."},
{"i": 1640, "domain": "public_safety", "summary": "World Bank women with no functional difficulty subjected to violence in last 12 months by country."},
{"i": 1641, "domain": "public_safety", "summary": "World Bank rural women with no functional difficulty subjected to violence in last 12 months by country."},
{"i": 1642, "domain": "public_safety", "summary": "World Bank urban women with no functional difficulty subjected to violence in last 12 months by country."},
{"i": 1643, "domain": "public_safety", "summary": "World Bank women aged 15-29 with none or some functional difficulty subjected to violence in last 12 months by country."},
{"i": 1644, "domain": "public_safety", "summary": "World Bank women aged 30-44 with none or some functional difficulty subjected to violence in last 12 months by country."},
{"i": 1645, "domain": "public_safety", "summary": "World Bank women with none or some functional difficulty subjected to violence in last 12 months by country."},
{"i": 1646, "domain": "public_safety", "summary": "World Bank rural women with none or some functional difficulty subjected to violence in last 12 months by country."},
{"i": 1647, "domain": "public_safety", "summary": "World Bank urban women with none or some functional difficulty subjected to violence in last 12 months by country."},
{"i": 1648, "domain": "public_safety", "summary": "World Bank women aged 15-29 with some functional difficulty subjected to violence in last 12 months by country."},
{"i": 1649, "domain": "public_safety", "summary": "World Bank women aged 30-44 with some functional difficulty subjected to violence in last 12 months by country."},
{"i": 1650, "domain": "public_safety", "summary": "World Bank women with some functional difficulty subjected to violence in last 12 months by country."},
{"i": 1651, "domain": "public_safety", "summary": "World Bank rural women with some functional difficulty subjected to violence in last 12 months by country."},
{"i": 1652, "domain": "public_safety", "summary": "World Bank urban women with some functional difficulty subjected to violence in last 12 months by country."},
{"i": 1672, "domain": "education", "summary": "World Bank Barro-Lee percent of population age 15+ with no education by country."},
{"i": 1678, "domain": "education", "summary": "World Bank Barro-Lee percent of population age 25+ with no education by country."},
{"i": 1698, "domain": "education", "summary": "World Bank Barro-Lee percent of population age 75+ with no education by country."},
{"i": 1819, "domain": "education", "summary": "World Bank Barro-Lee percent of female population age 15-19 with incomplete primary schooling by country."}
]
